MANIFEST.in
setup.py
nago/__init__.py
nago/__init__.pyc
nago/authentication.pyc
nago.egg-info/PKG-INFO
nago.egg-info/SOURCES.txt
nago.egg-info/dependency_links.txt
nago.egg-info/top_level.txt
nago/core/__init__.py
nago/core/__init__.pyc
nago/extensions/__init__.py
nago/extensions/__init__.pyc
nago/extensions/agent.py
nago/extensions/agent.pyc
nago/extensions/checkresults.py
nago/extensions/checkresults.pyc
nago/extensions/facts.py
nago/extensions/facts.pyc
nago/extensions/info.py
nago/extensions/info.pyc
nago/extensions/nodes.py
nago/extensions/nodes.pyc
nago/extensions/plugins.py
nago/extensions/plugins.pyc
nago/extensions/settings.py
nago/extensions/settings.pyc
nago/protocols/__init__.py
nago/protocols/__init__.pyc
nago/protocols/httpserver/__init__.py
nago/protocols/httpserver/__init__.pyc
nago/protocols/httpserver/templates/403.html
nago/protocols/httpserver/templates/index.html
nago/protocols/httpserver/templates/login.html
nago/protocols/httpserver/templates/node_detail.html
nago/protocols/httpserver/templates/nodes.html
nago/settings/__init__.py
scripts/nago