Metadata-Version: 1.1
Name: nago
Version: 1.6
Summary: General purpose agent, mostly used with nagios
Home-page: http://github.com/opinkerfi/nago
Author: Pall Sigurdsson
Author-email: palli@opensource.is
License: GPL
Platform: UNKNOWN
Requires: flask
Requires: simplejson
Requires: pynag
Requires: requests
